spade/__init__.py
spade/__main__.py
spade/cli.py
spade/commands/dig.py
spade/commands/traceroute.py
spade/error/core.py
spade/error/dig.py
spade/error/traceroute.py
spade/templates/dig/zone_file.txt
spade_cli-0.2.4.dist-info/entry_points.txt
spade_cli-0.2.4.dist-info/WHEEL
spade_cli-0.2.4.dist-info/METADATA
spade_cli-0.2.4.dist-info/RECORD
