Metadata-Version: 2.1
Name: spade-cli
Version: 0.2.4
Summary: You can't dig without a spade! - a super-powered networking tool!
License: MIT
Author: Vivaan Verma
Author-email: hello@vivaanverma.com
Requires-Python: >=3.10,<4.0
Classifier: License :: OSI Approved :: MIT License
Classifier: Programming Language :: Python :: 3
Classifier: Programming Language :: Python :: 3.10
Requires-Dist: dnspython (>=2.0,<3.0)
Requires-Dist: icmplib (>=3.0.2,<4.0.0)
Requires-Dist: ipwhois (>=1.2.0,<2.0.0)
Requires-Dist: pydantic (>=1.8,<2.0)
Requires-Dist: rich (>=10.14,<11.0)
Requires-Dist: typer[all] (>=0.4.0,<0.5.0)
